README.rst
setup.py
iconf/__init__.py
iconf.egg-info/PKG-INFO
iconf.egg-info/SOURCES.txt
iconf.egg-info/dependency_links.txt
iconf.egg-info/not-zip-safe
iconf.egg-info/top_level.txt