Metadata-Version: 1.1
Name: iconf
Version: 0.0.2
Summary: Simple method used to load configuration variables from different sources.
Home-page: https://github.com/adonisnafeh/iconf
Author: Adonis Nafeh
Author-email: adonisnafeh@gmail.com
License: UNKNOWN
Download-URL: https://github.com/adonisnafeh/iconf/tarball/master
Keywords: json,django settings,configuration,loader,environment variables,ci server,continuous integration,circle ci,travis ci,jenkins
Platform: UNKNOWN
Classifier: Development Status :: 5 - Production/Stable
Classifier: Environment :: Web Environment
Classifier: Intended Audience :: Developers
Classifier: License :: OSI Approved :: BSD License
Classifier: Topic :: Software Development :: Libraries :: Python Modules
Classifier: Programming Language :: Python
Classifier: Programming Language :: Python :: 2.7
Classifier: Programming Language :: Python :: 3
Classifier: Programming Language :: Python :: 3.4
Classifier: Programming Language :: Python :: 3.5
Classifier: Programming Language :: Python :: 3.6
